{
  "$schema": "https://developer.microsoft.com/json-schemas/rush/v5/rush.schema.json",
  "rushVersion": "5.61.2",
  "pnpmVersion": "6.28.0",
  "pnpmOptions": {
    "strictPeerDependencies": true,
    "preventManualShrinkwrapChanges": true,
    "useWorkspaces": true
  },
  "nodeSupportedVersionRange": ">=12.0.0",
  "ensureConsistentVersions": true,
  "allowMostlyStandardPackageNames": true,
  "repository": {
    "url": "https://github.com/the-moebius/aws-toolkit",
    "defaultBranch": "main"
  },
  "projects": [
    {
      "packageName": "@moebius/aws-cw-log-streamer",
      "projectFolder": "packages/cw-log-streamer",
      "shouldPublish": false
    },
    {
      "packageName": "@moebius/aws-ecs-task-monitor",
      "projectFolder": "packages/ecs-task-monitor",
      "shouldPublish": false
    },
    {
      "packageName": "@moebius/aws-ecs-task-runner",
      "projectFolder": "packages/ecs-task-runner",
      "shouldPublish": false
    }
  ]
}
